test/__init__.py
test/test_matcher.py
test/test_ngrams.py
tfidf_matcher/__init__.py
tfidf_matcher/matcher.py
tfidf_matcher/ngrams.py
tfidf_matcher-0.3.0.dist-info/LICENSE
tfidf_matcher-0.3.0.dist-info/METADATA
tfidf_matcher-0.3.0.dist-info/WHEEL
tfidf_matcher-0.3.0.dist-info/top_level.txt
tfidf_matcher-0.3.0.dist-info/RECORD
