Metadata-Version: 2.1
Name: tfidf-matcher
Version: 0.3.0
Summary: A small package that enables super-fast TF-IDF based string matching.
Home-page: https://github.com/louistsiattalou/tfidf_matcher
Author: Louis Tsiattalou
Author-email: louis.tsi@gmail.com
Classifier: Programming Language :: Python :: 3
Classifier: License :: OSI Approved :: MIT License
Classifier: Operating System :: OS Independent
Requires-Python: >=3.5
License-File: LICENSE
Requires-Dist: scikit-learn
Requires-Dist: pandas
